[
  {"op": "remove", "path": "/machine/network"},
  {"op": "add", "path": "/machine/network", "value":
    {
      "hostname": "ZZ_HOSTNAME",
      "interfaces": [
        {
          "interface": "eth0",
          "dhcp": true,
          "mtu": 1500,
          "vip": {
            "ip": "10.0.40.80"
          }
        }
      ]
    }
  },
  {"op": "replace", "path": "/machine/time", "value":
    {
      "disabled": false,
      "servers": [
        "time.cloudflare.com"
      ]
    }
  },
  {"op": "add", "path": "/machine/kubelet/extraArgs", "value":
    {
      "feature-gates": "MixedProtocolLBService=true",
      "rotate-server-certificates": true
    }
  },
  {"op": "add", "path": "/cluster/proxy/disabled", "value": true },
  {"op": "add", "path": "/cluster/network/cni", "value":
    {
      "name": "custom",
      "urls": [
        "https://raw.githubusercontent.com/szinn/k8s-homelab/main/setup/talos/staging/cilium-quick-install.yaml"
      ]
    }
  },
  {"op": "add", "path": "/cluster/controllerManager/extraArgs", "value":
    {
      "bind-address": "0.0.0.0"
    }
  },
  {"op": "add", "path": "/cluster/scheduler/extraArgs", "value":
    {
      "bind-address": "0.0.0.0"
    }
  },
  {"op": "replace", "path": "/cluster/extraManifests", "value":[
    "https://raw.githubusercontent.com/alex1989hu/kubelet-serving-cert-approver/v0.3.0/deploy/ha-install.yaml",
    "https://github.com/kubernetes-sigs/metrics-server/releases/latest/download/components.yaml"
  ]},
  {"op": "replace", "path": "/cluster/network/podSubnets/0", "value": "10.50.0.0/16"},
  {"op": "replace", "path": "/cluster/network/serviceSubnets/0", "value": "10.51.0.0/16"}
]
